craftxpy/__init__.py
craftxpy/agents/__init__.py
craftxpy/agents/router.py
craftxpy/memory/__init__.py
craftxpy/memory/config.py
craftxpy/memory/logger.py
craftxpy/memory/storage.py
craftxpy/plugins/__init__.py
craftxpy/plugins/base.py
craftxpy/plugins/tools/__init__.py
craftxpy/plugins/tools/file_hydration.py
craftxpy/plugins/tools/large_storage_manager.py
craftxpy/utils/__init__.py
craftxpy/utils/page_builder.py
craftxpy/utils/shell.py
tests/__init__.py
tests/conftest.py
tests/test_router.py
tests/test_ui.py
tests/test_website.py
craftxpy-0.1.2.dist-info/LICENSE
craftxpy-0.1.2.dist-info/METADATA
craftxpy-0.1.2.dist-info/WHEEL
craftxpy-0.1.2.dist-info/entry_points.txt
craftxpy-0.1.2.dist-info/top_level.txt
craftxpy-0.1.2.dist-info/RECORD
